upstox_totp/__init__.py
upstox_totp/cli.py
upstox_totp/client.py
upstox_totp/errors.py
upstox_totp/logging.py
upstox_totp/models.py
upstox_totp/py.typed
upstox_totp/_api/__init__.py
upstox_totp/_api/app_token.py
upstox_totp/_api/base.py
upstox_totp-1.0.8.dist-info/METADATA
upstox_totp-1.0.8.dist-info/WHEEL
upstox_totp-1.0.8.dist-info/entry_points.txt
upstox_totp-1.0.8.dist-info/licenses/LICENSE
upstox_totp-1.0.8.dist-info/RECORD
