Metadata-Version: 2.4
Name: upstox-totp
Version: 1.0.8
Summary: A lightweight Python package that simplifies Upstox API authentication by handling TOTP-based login and token generation automatically. With this library, you can securely generate and refresh access tokens required to connect to the Upstox trading platform without manual intervention.
Project-URL: Homepage, https://github.com/batpool/upstox-totp
Project-URL: Repository, https://github.com/batpool/upstox-totp
Project-URL: Issues, https://github.com/batpool/upstox-totp/issues
Project-URL: Reddit, https://www.reddit.com/user/iamdeadloop/
Project-URL: Documentation, https://upstox-totp.readthedocs.io/
Author-email: batpool <satyabrata.7059@gmail.com>
License: MIT License
License-File: LICENSE
Keywords: 2fa,access-token,algorithmic-trading,api,api-authentication,api-client,api-sdk,api-token,authentication,authenticator,automated-login,automation,broker,brokerage,bse,cli,command-line,credentials,crypto,cryptocurrency,currency,derivatives,equities,equity,finance,financial,financial-api,fintech,forex,futures,india-trading,indian-stock-market,investing,investment,login,market-api,market-data,nse,one-time-password,options,otp,portfolio,python-trading,quantitative-trading,secure,securities,
Classifier: Development Status :: 4 - Beta
Classifier: Environment :: Console
Classifier: Intended Audience :: Developers
Classifier: Intended Audience :: Financial and Insurance Industry
Classifier: License :: OSI Approved :: MIT License
Classifier: Natural Language :: English
Classifier: Operating System :: OS Independent
Classifier: Programming Language :: Python :: 3
Classifier: Programming Language :: Python :: 3 :: Only
Classifier: Programming Language :: Python :: 3.12
Classifier: Programming Language :: Python :: 3.13
Classifier: Topic :: Internet :: WWW/HTTP :: Dynamic Content
Classifier: Topic :: Internet :: WWW/HTTP :: Session
Classifier: Topic :: Office/Business :: Financial
Classifier: Topic :: Office/Business :: Financial :: Investment
Classifier: Topic :: Security
Classifier: Topic :: Security :: Cryptography
Classifier: Topic :: Software Development :: Libraries :: Application Frameworks
Classifier: Topic :: Software Development :: Libraries :: Python Modules
Classifier: Topic :: System :: Systems Administration :: Authentication/Directory
Classifier: Typing :: Typed
Requires-Python: >=3.12
Requires-Dist: click>=8.3.0
Requires-Dist: curl-cffi>=0.13.0
Requires-Dist: dotenv>=0.9.9
Requires-Dist: pydantic>=2.11.9
Requires-Dist: pyotp>=2.9.0
